Workbook

Sheet Instructions
A1: Vitora Financial Scenario Model
A3: How to use
A4: 1. Change blue input cells in the Inputs tab to test scenarios.
A5: 2. Review customer growth, costs, P&L, and funding headroom in the other tabs.
A6: 3. Clinics and hospitals are shared tenants; only enterprise customers use dedicated environments.
A7: 4. This is an annual planning model. Add a monthly collections and working-capital model before fundraising decisions.

Sheet Inputs
A1: Scenario Inputs
A2: Input | B2: Y1 | C2: Y2 | D2: Y3 | E2: Y4 | F2: Y5
A3: Scenario revenue multiplier | B3: 1 | C3: 1 | D3: 1 | E3: 1 | F3: 1
A4: Scenario cost multiplier | B4: 1 | C4: 1 | D4: 1 | E4: 1 | F4: 1
A5: Scenario new-customer multiplier | B5: 1 | C5: 1 | D5: 1 | E5: 1 | F5: 1
A6: Total FTE | B6: 6 | C6: 11 | D6: 19 | E6: 26 | F6: 33
A7: All-in FTE cost per month (KES) | B7: 100000 | C7: 100000 | D7: 100000 | E7: 100000 | F7: 100000
A8: Shared cloud baseline per month (KES) | B8: 80000 | C8: 80000 | D8: 80000 | E8: 80000 | F8: 80000
A9: Shared tenant cloud per month (KES) | B9: 100 | C9: 100 | D9: 100 | E9: 100 | F9: 100
A10: Enterprise cloud per month (KES) | B10: 10000 | C10: 10000 | D10: 10000 | E10: 10000 | F10: 10000
A11: Clinic variable CAC (KES) | B11: 45000 | C11: 45000 | D11: 45000 | E11: 45000 | F11: 45000
A12: Hospital variable CAC (KES) | B12: 130000 | C12: 130000 | D12: 130000 | E12: 130000 | F12: 130000
A13: Enterprise variable CAC (KES) | B13: 260000 | C13: 260000 | D13: 260000 | E13: 260000 | F13: 260000
A14: Clinic onboarding (KES) | B14: 5000 | C14: 5000 | D14: 5000 | E14: 5000 | F14: 5000
... A23: KES per US dollar | B23: 130 | C23: 130 | D23: 130 | E23: 130 | F23: 130

Sheet Customers
A1: Customer Growth and Revenue
A2: Metric | B2: Y1 | C2: Y2 | D2: Y3 | E2: Y4 | F2: Y5
A3: New clinics | B3: 15 | C3: 55 | D3: 120 | E3: 180 | F3: 234
A4: New hospitals | B4: 3 | C4: 14 | D4: 40 | E4: 48 | F4: 60
A5: New enterprise | B5: 0 | C5: 3 | D5: 6 | E5: 9 | F5: 12
A6: Churned customers | B6: 3 | C6: 9 | D6: 19 | E6: 24 | F6: 29
A7: Ending clinics | B7: 12 | C7: 58 | D7: 160 | E7: 320 | F7: 525
A8: Ending hospitals | B8: 3 | C8: 17 | D8: 56 | E8: 100 | F8: 160
A9: Ending enterprise | B9: 0 | C9: 3 | D9: 9 | E9: 18 | F9: 30
A10: Total active customers | B10: 15 | C10: 78 | D10: 225 | E10: 438 | F10: 715
A11: Clinic MRR incl. expected add-ons (KES) | B11: =8999+'Add-ons'!$B$8 | C11: =8999+'Add-ons'!$B$8 | D11: =8999+'Add-ons'!$B$8 | E11: =8999+'Add-ons'!$B$8 | F11: =8999+'Add-ons'!$B$8
A12: Hospital MRR incl. expected add-ons (KES) | B12: =49999+'Add-ons'!$B$8 | C12: =49999+'Add-ons'!$B$8 | D12: =49999+'Add-ons'!$B$8 | E12: =49999+'Add-ons'!$B$8 | F12: =49999+'Add-ons'!$B$8
A13: Enterprise MRR incl. expected add-ons (KES) | B13: =80000+'Add-ons'!$B$8 | C13: =80000+'Add-ons'!$B$8 | D13: =80000+'Add-ons'!$B$8 | E13: =80000+'Add-ons'!$B$8 | F13: =80000+'Add-ons'!$B$8
A15: Average clinics | B15: =B7/2 | C15: =(B7+C7)/2 | D15: =(C7+D7)/2 | E15: =(D7+E7)/2 | F15: =(E7+F7)/2
A16: Average hospitals | B16: =B8/2 | C16: =(B8+C8)/2 | D16: =(C8+D8)/2 | E16: =(D8+E8)/2 | F16: =(E8+F8)/2
A17: Average enterprise | B17: =B9/2 | C17: =(B9+C9)/2 | D17: =(C9+D9)/2 | E17: =(D9+E9)/2 | F17: =(E9+F9)/2
A18: Annual revenue (KES) | B18: =((B15*B11*12)+(B16*B12*12)+(B17*B13*12))*Inputs!B3 | C18: =((C15*C11*12)+(C16*C12*12)+(C17*C13*12))*Inputs!C3 | D18: =((D15*D11*12)+(D16*D12*12)+(D17*D13*12))*Inputs!D3 | E18: =((E15*E11*12)+(E16*E12*12)+(E17*E13*12))*Inputs!E3 | F18: =((F15*F11*12)+(F16*F12*12)+(F17*F13*12))*Inputs!F3

Sheet Costs
A1: Driver-Based Costs
A2: Cost Category | B2: Y1 | C2: Y2 | D2: Y3 | E2: Y4 | F2: Y5
A3: Product, commercial, and G&A payroll (KES) | B3: =(Inputs!B6-1)*Inputs!B7*12 | C3: =(Inputs!C6-2)*Inputs!C7*12 | D3: =(Inputs!D6-3)*Inputs!D7*12 | E3: =(Inputs!E6-5)*Inputs!E7*12 | F3: =(Inputs!F6-7)*Inputs!F7*12
A4: Support payroll in delivery COGS (KES) | B4: =1*Inputs!B7*12 | C4: =2*Inputs!C7*12 | D4: =3*Inputs!D7*12 | E4: =5*Inputs!E7*12 | F4: =7*Inputs!F7*12
A5: Shared cloud platform (KES) | B5: =Inputs!B8*12+((Customers!B15+Customers!B16)*Inputs!B9*12) | C5: =Inputs!C8*12+((Customers!C15+Customers!C16)*Inputs!C9*12) | D5: =Inputs!D8*12+((Customers!D15+Customers!D16)*Inputs!D9*12) | E5: =Inputs!E8*12+((Customers!E15+Customers!E16)*Inputs!E9*12) | F5: =Inputs!F8*12+((Customers!F15+Customers!F16)*Inputs!F9*12)
A6: Enterprise cloud environments (KES) | B6: =Customers!B17*Inputs!B10*12 | C6: =Customers!C17*Inputs!C10*12 | D6: =Customers!D17*Inputs!D10*12 | E6: =Customers!E17*Inputs!E10*12 | F6: =Customers!F17*Inputs!F10*12
A7: Sales and marketing spend (KES) | B7: =Inputs!B21 | C7: =Inputs!C21 | D7: =Inputs!D21 | E7: =Inputs!E21 | F7: =Inputs!F21
A8: Shared tenant onboarding (KES) | B8: =Customers!B3*Inputs!B14+Customers!B4*Inputs!B15 | C8: =Customers!C3*Inputs!C14+Customers!C4*Inputs!C15 | D8: =Customers!D3*Inputs!D14+Customers!D4*Inputs!D15 | E8: =Customers!E3*Inputs!E14+Customers!E4*Inputs!E15 | F8: =Customers!F3*Inputs!F14+Customers!F4*Inputs!F15
A9: Enterprise deployment (KES) | B9: =Customers!B5*Inputs!B16 | C9: =Customers!C5*Inputs!C16 | D9: =Customers!D5*Inputs!D16 | E9: =Customers!E5*Inputs!E16 | F9: =Customers!F5*Inputs!F16
A10: Shared release and enablement (KES) | B10: =Inputs!B17 | C10: =Inputs!C17 | D10: =Inputs!D17 | E10: =Inputs!E17 | F10: =Inputs!F17
A11: Office and G&A (KES) | B11: =Inputs!B18 | C11: =Inputs!C18 | D11: =Inputs!D18 | E11: =Inputs!E18 | F11: =Inputs!F18
A12: Legal, compliance, and governance (KES) | B12: =Inputs!B19 | C12: =Inputs!C19 | D12: =Inputs!D19 | E12: =Inputs!E19 | F12: =Inputs!F19
A13: TibaBot delivery reserve (KES) | B13: =Inputs!B20 | C13: =Inputs!C20 | D13: =Inputs!D20 | E13: =Inputs!E20 | F13: =Inputs!F20
A14: Total operating costs (KES) | B14: =SUM(B3:B13)*Inputs!B4 | C14: =SUM(C3:C13)*Inputs!C4 | D14: =SUM(D3:D13)*Inputs!D4 | E14: =SUM(E3:E13)*Inputs!E4 | F14: =SUM(F3:F13)*Inputs!F4
A15: Delivery COGS (KES) | B15: =SUM(B4:B6,B8:B10,B13)*Inputs!B4 | C15: =SUM(C4:C6,C8:C10,C13)*Inputs!C4 | D15: =SUM(D4:D6,D8:D10,D13)*Inputs!D4 | E15: =SUM(E4:E6,E8:E10,E13)*Inputs!E4 | F15: =SUM(F4:F6,F8:F10,F13)*Inputs!F4

Sheet Profit and Loss
A1: Profit and Loss
A2: Metric | B2: Y1 | C2: Y2 | D2: Y3 | E2: Y4 | F2: Y5
A3: Revenue (KES) | B3: =Customers!B18 | C3: =Customers!C18 | D3: =Customers!D18 | E3: =Customers!E18 | F3: =Customers!F18
A4: Delivery COGS (KES) | B4: =Costs!B15 | C4: =Costs!C15 | D4: =Costs!D15 | E4: =Costs!E15 | F4: =Costs!F15
A5: Gross profit (KES) | B5: =B3-B4 | C5: =C3-C4 | D5: =D3-D4 | E5: =E3-E4 | F5: =F3-F4
A6: Gross margin | B6: =IFERROR(B5/B3,0) | C6: =IFERROR(C5/C3,0) | D6: =IFERROR(D5/D3,0) | E6: =IFERROR(E5/E3,0) | F6: =IFERROR(F5/F3,0)
A7: Operating costs (KES) | B7: =Costs!B14 | C7: =Costs!C14 | D7: =Costs!D14 | E7: =Costs!E14 | F7: =Costs!F14
A8: EBITDA (KES) | B8: =B3-B7 | C8: =C3-C7 | D8: =D3-D7 | E8: =E3-E7 | F8: =F3-F7
A9: Cumulative operating result (KES) | B9: =B8 | C9: =B9+C8 | D9: =C9+D8 | E9: =D9+E8 | F9: =E9+F8
A10: Funding headroom (KES) | B10: =Inputs!B22+MIN($B$9:B9) | C10: =Inputs!C22+MIN($B$9:C9) | D10: =Inputs!D22+MIN($B$9:D9) | E10: =Inputs!E22+MIN($B$9:E9) | F10: =Inputs!F22+MIN($B$9:F9)

Sheet Dashboard
A1: Scenario Dashboard
A3: Metric | B3: Base scenario output
A4: Peak operating deficit (KES) | B4: =-MIN('Profit and Loss'!B9:F9)
A5: Peak operating deficit (USD) | B5: =B4/Inputs!B23
A6: Funding tranche (KES) | B6: =Inputs!B22
A7: Annual-model headroom (KES) | B7: =B6-B4
A8: First positive EBITDA year | B8: =IF('Profit and Loss'!B8>0,"Y1",IF('Profit and Loss'!C8>0,"Y2",IF('Profit and Loss'!D8>0,"Y3",IF('Profit and Loss'!E8>0,"Y4","Y5"))))
A9: Year 5 EBITDA (KES) | B9: ='Profit and Loss'!F8
A10: Year 5 active customers | B10: =Customers!F10
A12: Scenario controls
A13: Edit Inputs!B3:F5 to test revenue, cost, and customer-growth multipliers.

Sheet Add-ons
A1: Add-On Module Logic
A2: Module | B2: Monthly price (KES) | C2: Attach rate | D2: Expected MRR contribution (KES)
A3: TibaBot AI | B3: 5000 | C3: 0.35 | D3: =B3*C3
A4: Offline Sync | B4: 3000 | C4: 0.45 | D4: =B4*C4
A5: Advanced LIS | B5: 7000 | C5: 0.2 | D5: =B5*C5
A6: SMS & WhatsApp | B6: 2500 | C6: =0.25 | D6: =B6*C6
A8: Expected add-on MRR per customer (KES) | B8: =SUM(D3:D6)
A10: Use
A11: Update prices and attach rates to simulate add-on adoption. Customer MRR in the Customers tab updates automatically.
